setup.py
format_converter/__init__.py
format_converter.egg-info/PKG-INFO
format_converter.egg-info/SOURCES.txt
format_converter.egg-info/dependency_links.txt
format_converter.egg-info/requires.txt
format_converter.egg-info/top_level.txt